<?xml version="1.0" encoding="utf-8"?>
<Dependencies>

  <ProductDependencies>
  </ProductDependencies>

  <ToolsetDependencies>
    <Dependency Name="Microsoft.DotNet.Arcade.Sdk" Version="9.0.0-beta.24429.5">
      <Uri>https://github.com/dotnet/arcade</Uri>
      <Sha>d21db44e84b9038ea7b2add139adee2303d46800</Sha>
      <SourceBuild RepoName="arcade" ManagedOnly="true" />
    </Dependency>

    <Dependency Name="Microsoft.DotNet.Helix.Sdk" Version="9.0.0-beta.24429.5">
      <Uri>https://github.com/dotnet/arcade</Uri>
      <Sha>d21db44e84b9038ea7b2add139adee2303d46800</Sha>
    </Dependency>
  </ToolsetDependencies>

</Dependencies>
